{
    "total": [
        {
            "id": "100058447002356",
            "count": 4
        },
        {
            "id": "100061996433763",
            "count": 0
        },
        {
            "id": "100088479528644",
            "count": 0
        },
        {
            "id": "100089554735811",
            "count": 5
        },
        {
            "id": "100088405534088",
            "count": 20
        },
        {
            "id": "100067500315224",
            "count": 25
        },
        {
            "id": "100082947335897",
            "count": 65
        },
        {
            "id": "100085309687792",
            "count": 19
        },
        {
            "id": "100091927535256",
            "count": 101
        },
        {
            "id": "100088521867968",
            "count": 77
        },
        {
            "id": "100084482003404",
            "count": 2
        },
        {
            "id": "100076834916779",
            "count": 15
        },
        {
            "id": "100082579010871",
            "count": 63
        },
        {
            "id": "100071682956138",
            "count": 119
        },
        {
            "id": "100091487138039",
            "count": 92
        },
        {
            "id": "100080911189131",
            "count": 117
        },
        {
            "id": "100091859088664",
            "count": 5
        },
        {
            "id": "100076164439617",
            "count": 1
        },
        {
            "id": "100078135785731",
            "count": 27
        },
        {
            "id": "100081542217160",
            "count": 48
        },
        {
            "id": "100083734571348",
            "count": 4
        },
        {
            "id": "100067103332231",
            "count": 115
        },
        {
            "id": "100085095313152",
            "count": 1
        },
        {
            "id": "100069950370304",
            "count": 18
        },
        {
            "id": "100085358693129",
            "count": 1
        },
        {
            "id": "100047693581012",
            "count": 51
        }
    ],
    "week": [
        {
            "id": "100058447002356",
            "count": 1,
            "name": "Callie Y'vrsk"
        },
        {
            "id": "100061996433763",
            "count": 0,
            "name": "Jasper Igop II"
        },
        {
            "id": "100088479528644",
            "count": 0,
            "name": "ZAY CAELUM LEIF"
        },
        {
            "id": "100089554735811",
            "count": 5
        },
        {
            "id": "100088405534088",
            "count": 20
        },
        {
            "id": "100067500315224",
            "count": 25
        },
        {
            "id": "100082947335897",
            "count": 65
        },
        {
            "id": "100085309687792",
            "count": 19
        },
        {
            "id": "100091927535256",
            "count": 101
        },
        {
            "id": "100088521867968",
            "count": 77
        },
        {
            "id": "100084482003404",
            "count": 2
        },
        {
            "id": "100076834916779",
            "count": 15
        },
        {
            "id": "100082579010871",
            "count": 63
        },
        {
            "id": "100071682956138",
            "count": 119
        },
        {
            "id": "100091487138039",
            "count": 92
        },
        {
            "id": "100080911189131",
            "count": 117
        },
        {
            "id": "100091859088664",
            "count": 5
        },
        {
            "id": "100076164439617",
            "count": 1
        },
        {
            "id": "100078135785731",
            "count": 27
        },
        {
            "id": "100081542217160",
            "count": 48
        },
        {
            "id": "100083734571348",
            "count": 4
        },
        {
            "id": "100067103332231",
            "count": 115
        },
        {
            "id": "100085095313152",
            "count": 1
        },
        {
            "id": "100069950370304",
            "count": 18
        },
        {
            "id": "100085358693129",
            "count": 1
        },
        {
            "id": "100047693581012",
            "count": 51
        }
    ],
    "day": [
        {
            "id": "100058447002356",
            "count": 1,
            "name": "Callie Y'vrsk"
        },
        {
            "id": "100061996433763",
            "count": 0,
            "name": "Jasper Igop II"
        },
        {
            "id": "100088479528644",
            "count": 0,
            "name": "ZAY CAELUM LEIF"
        },
        {
            "id": "100089554735811",
            "count": 5
        },
        {
            "id": "100088405534088",
            "count": 20
        },
        {
            "id": "100067500315224",
            "count": 25
        },
        {
            "id": "100082947335897",
            "count": 65
        },
        {
            "id": "100085309687792",
            "count": 19
        },
        {
            "id": "100091927535256",
            "count": 101
        },
        {
            "id": "100088521867968",
            "count": 77
        },
        {
            "id": "100084482003404",
            "count": 2
        },
        {
            "id": "100076834916779",
            "count": 15
        },
        {
            "id": "100082579010871",
            "count": 63
        },
        {
            "id": "100071682956138",
            "count": 119
        },
        {
            "id": "100091487138039",
            "count": 92
        },
        {
            "id": "100080911189131",
            "count": 117
        },
        {
            "id": "100091859088664",
            "count": 5
        },
        {
            "id": "100076164439617",
            "count": 1
        },
        {
            "id": "100078135785731",
            "count": 27
        },
        {
            "id": "100081542217160",
            "count": 48
        },
        {
            "id": "100083734571348",
            "count": 4
        },
        {
            "id": "100067103332231",
            "count": 115
        },
        {
            "id": "100085095313152",
            "count": 1
        },
        {
            "id": "100069950370304",
            "count": 18
        },
        {
            "id": "100085358693129",
            "count": 1
        },
        {
            "id": "100047693581012",
            "count": 51
        }
    ],
    "time": 4
}