{
    "total": [
        {
            "id": "100015784159494",
            "count": 0
        },
        {
            "id": "100029946503614",
            "count": 0
        },
        {
            "id": "100052256795455",
            "count": 0
        },
        {
            "id": "100053613574876",
            "count": 10
        },
        {
            "id": "100056442510902",
            "count": 0
        },
        {
            "id": "100057336722373",
            "count": 0
        },
        {
            "id": "100063457657253",
            "count": 0
        },
        {
            "id": "100063756061243",
            "count": 0
        },
        {
            "id": "100067497300792",
            "count": 12
        },
        {
            "id": "100068296688286",
            "count": 0
        },
        {
            "id": "100068424046111",
            "count": 0
        },
        {
            "id": "100068750480443",
            "count": 12
        },
        {
            "id": "100068842388506",
            "count": 0
        },
        {
            "id": "100068888551337",
            "count": 0
        },
        {
            "id": "100069341480870",
            "count": 23
        },
        {
            "id": "100069347376706",
            "count": 0
        },
        {
            "id": "100069436000106",
            "count": 0
        },
        {
            "id": "100071147416496",
            "count": 0
        },
        {
            "id": "100072316457174",
            "count": 3
        },
        {
            "id": "100072333138502",
            "count": 0
        },
        {
            "id": "100072464087782",
            "count": 0
        },
        {
            "id": "100072861848340",
            "count": 0
        },
        {
            "id": "100072868715963",
            "count": 5
        },
        {
            "id": "100072990777373",
            "count": 0
        },
        {
            "id": "100073359132347",
            "count": 0
        },
        {
            "id": "100073923792201",
            "count": 0
        },
        {
            "id": "100074102111403",
            "count": 0
        },
        {
            "id": "100074788670733",
            "count": 0
        },
        {
            "id": "100075056864256",
            "count": 0
        },
        {
            "id": "100075194042673",
            "count": 2
        },
        {
            "id": "100075283802656",
            "count": 0
        },
        {
            "id": "100076171426141",
            "count": 25
        },
        {
            "id": "100076236396452",
            "count": 0
        },
        {
            "id": "100076441082770",
            "count": 28
        },
        {
            "id": "100076661327214",
            "count": 0
        },
        {
            "id": "100076714233578",
            "count": 0
        },
        {
            "id": "100076834916779",
            "count": 54
        },
        {
            "id": "100078010357356",
            "count": 20
        },
        {
            "id": "100078720609713",
            "count": 0
        },
        {
            "id": "100079021125349",
            "count": 0
        },
        {
            "id": "100079075326714",
            "count": 0
        },
        {
            "id": "100079345951320",
            "count": 0
        },
        {
            "id": "100079539530322",
            "count": 0
        },
        {
            "id": "100079900270483",
            "count": 0
        },
        {
            "id": "100080027797495",
            "count": 0
        },
        {
            "id": "100080034333694",
            "count": 0
        },
        {
            "id": "100080597322059",
            "count": 0
        },
        {
            "id": "100080684537023",
            "count": 0
        },
        {
            "id": "100080694881574",
            "count": 8
        },
        {
            "id": "100080743230165",
            "count": 0
        },
        {
            "id": "100081178122673",
            "count": 0
        },
        {
            "id": "100081370230661",
            "count": 33
        },
        {
            "id": "100081499382300",
            "count": 0
        },
        {
            "id": "100081542657328",
            "count": 0
        },
        {
            "id": "100081819391260",
            "count": 11
        },
        {
            "id": "100081844080766",
            "count": 0
        },
        {
            "id": "100082005732944",
            "count": 0
        },
        {
            "id": "100082185965096",
            "count": 0
        },
        {
            "id": "100082693570014",
            "count": 21
        },
        {
            "id": "100082996149404",
            "count": 0
        },
        {
            "id": "100083222048188",
            "count": 3
        },
        {
            "id": "100083314337739",
            "count": 1
        },
        {
            "id": "100083320056754",
            "count": 0
        },
        {
            "id": "100083825834857",
            "count": 2
        },
        {
            "id": "100083964785167",
            "count": 0
        },
        {
            "id": "100084182315788",
            "count": 0
        },
        {
            "id": "100084383060995",
            "count": 0
        },
        {
            "id": "100084440292351",
            "count": 0
        },
        {
            "id": "100084548494927",
            "count": 0
        },
        {
            "id": "100084846044769",
            "count": 0
        },
        {
            "id": "100085230758202",
            "count": 0
        },
        {
            "id": "100085236265871",
            "count": 0
        },
        {
            "id": "100085255144447",
            "count": 0
        },
        {
            "id": "100085290743793",
            "count": 2
        },
        {
            "id": "100085327013500",
            "count": 13
        },
        {
            "id": "100085614473846",
            "count": 0
        },
        {
            "id": "100085660627867",
            "count": 0
        },
        {
            "id": "100085831004499",
            "count": 0
        },
        {
            "id": "100086067229638",
            "count": 0
        },
        {
            "id": "100086333457652",
            "count": 0
        },
        {
            "id": "100086705957333",
            "count": 0
        },
        {
            "id": "100086730093729",
            "count": 15
        },
        {
            "id": "100086873086028",
            "count": 0
        },
        {
            "id": "100087242479229",
            "count": 0
        },
        {
            "id": "100087269285806",
            "count": 0
        },
        {
            "id": "100087282854181",
            "count": 0
        },
        {
            "id": "100087417728849",
            "count": 0
        },
        {
            "id": "100087462635316",
            "count": 19
        },
        {
            "id": "100087487240107",
            "count": 0
        },
        {
            "id": "100087567420057",
            "count": 1
        },
        {
            "id": "100087635354804",
            "count": 0
        },
        {
            "id": "100087742362600",
            "count": 0
        },
        {
            "id": "100087757128483",
            "count": 0
        },
        {
            "id": "100088145014968",
            "count": 12
        },
        {
            "id": "100088213791023",
            "count": 0
        },
        {
            "id": "100088402937238",
            "count": 4
        },
        {
            "id": "100088479528644",
            "count": 0
        },
        {
            "id": "100088615035236",
            "count": 1
        },
        {
            "id": "100088665700748",
            "count": 0
        },
        {
            "id": "100088675755376",
            "count": 0
        },
        {
            "id": "100088887104351",
            "count": 2
        },
        {
            "id": "100089041035228",
            "count": 0
        },
        {
            "id": "100089071717121",
            "count": 0
        },
        {
            "id": "100089184803890",
            "count": 0
        },
        {
            "id": "100089259454697",
            "count": 2
        },
        {
            "id": "100089497879929",
            "count": 0
        },
        {
            "id": "100089612781246",
            "count": 0
        },
        {
            "id": "100089624544445",
            "count": 18
        },
        {
            "id": "100089662445770",
            "count": 0
        },
        {
            "id": "100089667812152",
            "count": 0
        },
        {
            "id": "100089695930708",
            "count": 9
        },
        {
            "id": "100089885145913",
            "count": 0
        },
        {
            "id": "100090010219479",
            "count": 1
        },
        {
            "id": "100090138493248",
            "count": 56
        },
        {
            "id": "100090214917584",
            "count": 0
        },
        {
            "id": "100090243831766",
            "count": 32
        },
        {
            "id": "100090260647959",
            "count": 0
        },
        {
            "id": "100090274616480",
            "count": 0
        },
        {
            "id": "100090497120742",
            "count": 3
        },
        {
            "id": "100090498295451",
            "count": 0
        },
        {
            "id": "100090555570299",
            "count": 0
        },
        {
            "id": "100090650585413",
            "count": 0
        },
        {
            "id": "100090654592691",
            "count": 0
        },
        {
            "id": "100090927241810",
            "count": 0
        },
        {
            "id": "100090992310125",
            "count": 0
        },
        {
            "id": "100091051124538",
            "count": 0
        },
        {
            "id": "100091152932437",
            "count": 0
        },
        {
            "id": "100091242920227",
            "count": 0
        },
        {
            "id": "100091305139263",
            "count": 0
        },
        {
            "id": "100091319792809",
            "count": 0
        },
        {
            "id": "100091431649260",
            "count": 0
        },
        {
            "id": "100091446380331",
            "count": 3
        },
        {
            "id": "100091470234760",
            "count": 0
        },
        {
            "id": "100091557675158",
            "count": 0
        },
        {
            "id": "100091566003651",
            "count": 0
        },
        {
            "id": "100091598535897",
            "count": 0
        },
        {
            "id": "100091636410574",
            "count": 0
        },
        {
            "id": "100091640991984",
            "count": 0
        },
        {
            "id": "100091689253576",
            "count": 0
        },
        {
            "id": "100091749618696",
            "count": 0
        },
        {
            "id": "100091792085936",
            "count": 0
        },
        {
            "id": "100091811263378",
            "count": 0
        },
        {
            "id": "100091845386011",
            "count": 0
        },
        {
            "id": "100091925269916",
            "count": 0
        },
        {
            "id": "100091942812158",
            "count": 0
        },
        {
            "id": "100091957926852",
            "count": 0
        },
        {
            "id": "100091959339187",
            "count": 0
        },
        {
            "id": "100091972303801",
            "count": 0
        },
        {
            "id": "100091982292949",
            "count": 0
        },
        {
            "id": "100092041630302",
            "count": 0
        },
        {
            "id": "100092096341168",
            "count": 0
        },
        {
            "id": "100092226960610",
            "count": 0
        },
        {
            "id": "100092290023448",
            "count": 0
        },
        {
            "id": "100092291899287",
            "count": 4
        },
        {
            "id": "100092347736695",
            "count": 0
        },
        {
            "id": "100092389236756",
            "count": 14
        },
        {
            "id": "100092423284488",
            "count": 0
        },
        {
            "id": "100092448420484",
            "count": 0
        },
        {
            "id": "100092555448025",
            "count": 24
        },
        {
            "id": "100092557936946",
            "count": 4
        },
        {
            "id": "100092623511356",
            "count": 0
        },
        {
            "id": "100092683999049",
            "count": 0
        },
        {
            "id": "100092729915933",
            "count": 13
        },
        {
            "id": "100092730618083",
            "count": 0
        },
        {
            "id": "100092744559305",
            "count": 0
        },
        {
            "id": "100092753822065",
            "count": 0
        },
        {
            "id": "100092869911648",
            "count": 0
        },
        {
            "id": "100092936231836",
            "count": 65
        },
        {
            "id": "100092982437773",
            "count": 0
        },
        {
            "id": "100093041253586",
            "count": 0
        },
        {
            "id": "100093209922752",
            "count": 3
        },
        {
            "id": "100093249843329",
            "count": 0
        },
        {
            "id": "100093281914725",
            "count": 0
        },
        {
            "id": "100093305431364",
            "count": 59
        },
        {
            "id": "100093316270634",
            "count": 13
        },
        {
            "id": "100093337959838",
            "count": 0
        },
        {
            "id": "100093343144940",
            "count": 0
        },
        {
            "id": "100079655854751",
            "count": 24
        },
        {
            "id": "100091342400216",
            "count": 5
        },
        {
            "id": "100056962911456",
            "count": 8
        }
    ],
    "week": [
        {
            "id": "100015784159494",
            "count": 0,
            "name": "Jhon Xyryll Samoy"
        },
        {
            "id": "100029946503614",
            "count": 0,
            "name": "Arnel Cabael Elecionez"
        },
        {
            "id": "100052256795455",
            "count": 0,
            "name": "Aizlo Gezu"
        },
        {
            "id": "100053613574876",
            "count": 0,
            "name": "Thraia Ycà Kriffney"
        },
        {
            "id": "100056442510902",
            "count": 0,
            "name": "Xeon Klien"
        },
        {
            "id": "100057336722373",
            "count": 0,
            "name": "Mayumi Oxford"
        },
        {
            "id": "100063457657253",
            "count": 0,
            "name": "Yassy Tuwsi Montreux"
        },
        {
            "id": "100063756061243",
            "count": 0,
            "name": "Kiel Dursero"
        },
        {
            "id": "100067497300792",
            "count": 0,
            "name": "Justin Z'arxio"
        },
        {
            "id": "100068296688286",
            "count": 0,
            "name": "Ken Ewo Smith Z'arxio"
        },
        {
            "id": "100068424046111",
            "count": 0,
            "name": "Axel Kai Seviller"
        },
        {
            "id": "100068750480443",
            "count": 0,
            "name": "Cressida Astrid"
        },
        {
            "id": "100068842388506",
            "count": 0,
            "name": "Krianquin Rae"
        },
        {
            "id": "100068888551337",
            "count": 0,
            "name": "Kd Ador"
        },
        {
            "id": "100069341480870",
            "count": 0,
            "name": "Maya Aria P'rrty"
        },
        {
            "id": "100069347376706",
            "count": 0,
            "name": "Yuno"
        },
        {
            "id": "100069436000106",
            "count": 0,
            "name": "Keilyn Echavez"
        },
        {
            "id": "100071147416496",
            "count": 0,
            "name": "Clint Medidas"
        },
        {
            "id": "100072316457174",
            "count": 0,
            "name": "Jeyv Cussea"
        },
        {
            "id": "100072333138502",
            "count": 0,
            "name": "Yvà Snowlly"
        },
        {
            "id": "100072464087782",
            "count": 0,
            "name": "Zyrine Claire Dela Cruz"
        },
        {
            "id": "100072861848340",
            "count": 0,
            "name": "Akhira Montefalcon"
        },
        {
            "id": "100072868715963",
            "count": 0,
            "name": "Saji Yvette Sj'rve"
        },
        {
            "id": "100072990777373",
            "count": 0,
            "name": "Unice Sløøpy"
        },
        {
            "id": "100073359132347",
            "count": 0,
            "name": "Enzo J'vgsk"
        },
        {
            "id": "100073923792201",
            "count": 0,
            "name": "Yxie Scjevor"
        },
        {
            "id": "100074102111403",
            "count": 0,
            "name": "Shiro Mistuoten"
        },
        {
            "id": "100074788670733",
            "count": 0,
            "name": "Devi Wu"
        },
        {
            "id": "100075056864256",
            "count": 0,
            "name": "Sebastian Cameron"
        },
        {
            "id": "100075194042673",
            "count": 0,
            "name": "Nixy Nixcy Hoe"
        },
        {
            "id": "100075283802656",
            "count": 0,
            "name": "Khier Quervø"
        },
        {
            "id": "100076171426141",
            "count": 0,
            "name": "Facebook user"
        },
        {
            "id": "100076236396452",
            "count": 0,
            "name": "Kylie Xylle Brythe"
        },
        {
            "id": "100076441082770",
            "count": 0,
            "name": "Kyle D'minahal"
        },
        {
            "id": "100076661327214",
            "count": 0,
            "name": "Scarlet D'oeuvro"
        },
        {
            "id": "100076714233578",
            "count": 0,
            "name": "Luce Claire Maude"
        },
        {
            "id": "100076834916779",
            "count": 0,
            "name": "Yanna Xyreen Hyvra"
        },
        {
            "id": "100078010357356",
            "count": 0,
            "name": "Zreiy Winz"
        },
        {
            "id": "100078720609713",
            "count": 0,
            "name": "Rocky Dump"
        },
        {
            "id": "100079021125349",
            "count": 0,
            "name": "Kathlyn Nipal ʚĩɞ"
        },
        {
            "id": "100079075326714",
            "count": 0,
            "name": "Dree Swæńj"
        },
        {
            "id": "100079345951320",
            "count": 0,
            "name": "Cyca Axerylle Alcantara"
        },
        {
            "id": "100079539530322",
            "count": 0,
            "name": "ۦۦ ۦۦ ۦۦ ۦۦ"
        },
        {
            "id": "100079900270483",
            "count": 0,
            "name": "Ezèkîel Lèrwîck Cruivo"
        },
        {
            "id": "100080027797495",
            "count": 0,
            "name": "Tyron Volkzki"
        },
        {
            "id": "100080034333694",
            "count": 0,
            "name": "Bella Z'arxia"
        },
        {
            "id": "100080597322059",
            "count": 0,
            "name": "Luke Natividad"
        },
        {
            "id": "100080684537023",
            "count": 0,
            "name": "Kyle Zeus Z'arxio"
        },
        {
            "id": "100080694881574",
            "count": 0,
            "name": "Kenzo Hiroshi"
        },
        {
            "id": "100080743230165",
            "count": 0,
            "name": "Rael Rivacci"
        },
        {
            "id": "100081178122673",
            "count": 0,
            "name": "Jasmin Guifre"
        },
        {
            "id": "100081370230661",
            "count": 0,
            "name": "Akishana Viara Liyunarez Ramirez"
        },
        {
            "id": "100081499382300",
            "count": 0,
            "name": "Raze Eziekiel Salvenia"
        },
        {
            "id": "100081542657328",
            "count": 0,
            "name": "Kristelle Monvalle"
        },
        {
            "id": "100081819391260",
            "count": 0,
            "name": "Nick's Dump"
        },
        {
            "id": "100081844080766",
            "count": 0,
            "name": "Prince Kurt Delasantos"
        },
        {
            "id": "100082005732944",
            "count": 0,
            "name": "Drake Savern Lee Z'arxio"
        },
        {
            "id": "100082185965096",
            "count": 0,
            "name": "Xian Winter"
        },
        {
            "id": "100082693570014",
            "count": 0,
            "name": "Yca Z'arxia"
        },
        {
            "id": "100082996149404",
            "count": 0,
            "name": "Kai S'jvrs"
        },
        {
            "id": "100083222048188",
            "count": 0,
            "name": "Tafi S'jdior"
        },
        {
            "id": "100083314337739",
            "count": 0,
            "name": "Chloe Jane Galvez"
        },
        {
            "id": "100083320056754",
            "count": 0,
            "name": "Clark Na Magaling"
        },
        {
            "id": "100083825834857",
            "count": 0,
            "name": "Cxion Z'arxia"
        },
        {
            "id": "100083964785167",
            "count": 0,
            "name": "Audrey Z'arxia"
        },
        {
            "id": "100084182315788",
            "count": 0,
            "name": "Averiah Hyacinth"
        },
        {
            "id": "100084383060995",
            "count": 0,
            "name": "Ban Dump"
        },
        {
            "id": "100084440292351",
            "count": 0,
            "name": "Maczine Shaile Livanne"
        },
        {
            "id": "100084548494927",
            "count": 0,
            "name": "Selene Sy"
        },
        {
            "id": "100084846044769",
            "count": 0,
            "name": "Luna Montero"
        },
        {
            "id": "100085230758202",
            "count": 0,
            "name": "Beatrice Fiøre"
        },
        {
            "id": "100085236265871",
            "count": 0,
            "name": "Le Ah Z'arxia"
        },
        {
            "id": "100085255144447",
            "count": 0,
            "name": "Yvio Vior"
        },
        {
            "id": "100085290743793",
            "count": 0,
            "name": "Kíbb Qúérvø"
        },
        {
            "id": "100085327013500",
            "count": 0,
            "name": "Xaiver J'vsk"
        },
        {
            "id": "100085614473846",
            "count": 0,
            "name": "Phia Shine"
        },
        {
            "id": "100085660627867",
            "count": 0,
            "name": "Kyle Smith"
        },
        {
            "id": "100085831004499",
            "count": 0,
            "name": "Sophia Kyle"
        },
        {
            "id": "100086067229638",
            "count": 0,
            "name": "Aeisha Z'arxia ʚĩɞ"
        },
        {
            "id": "100086333457652",
            "count": 0,
            "name": "JL Dilliger"
        },
        {
            "id": "100086705957333",
            "count": 0,
            "name": "Ashley Simp"
        },
        {
            "id": "100086730093729",
            "count": 0,
            "name": "Mikaella Samantha Park - Jung"
        },
        {
            "id": "100086873086028",
            "count": 0,
            "name": "Threia Fuentabella"
        },
        {
            "id": "100087242479229",
            "count": 0,
            "name": "Aekishe Zacharielle"
        },
        {
            "id": "100087269285806",
            "count": 0,
            "name": "Kurt Smit"
        },
        {
            "id": "100087282854181",
            "count": 0,
            "name": "Zhamella Sozaine"
        },
        {
            "id": "100087417728849",
            "count": 0,
            "name": "Akiesha Jvsk"
        },
        {
            "id": "100087462635316",
            "count": 0,
            "name": "Zabby Montefalco"
        },
        {
            "id": "100087487240107",
            "count": 0,
            "name": "Rei Z'arxio"
        },
        {
            "id": "100087567420057",
            "count": 0,
            "name": "Princess Althea"
        },
        {
            "id": "100087635354804",
            "count": 0,
            "name": "Leo Dum'p"
        },
        {
            "id": "100087742362600",
            "count": 0,
            "name": "Raine"
        },
        {
            "id": "100087757128483",
            "count": 0,
            "name": "Vierfaith Suarez"
        },
        {
            "id": "100088145014968",
            "count": 0,
            "name": "Xiana Soreen"
        },
        {
            "id": "100088213791023",
            "count": 0,
            "name": "Zarchia Dump"
        },
        {
            "id": "100088402937238",
            "count": 0,
            "name": "Zaxia Reighn Churo"
        },
        {
            "id": "100088479528644",
            "count": 0,
            "name": "ZAY CAELUM LEIF"
        },
        {
            "id": "100088615035236",
            "count": 0,
            "name": "Ashiro Kulangsamwamwamwa"
        },
        {
            "id": "100088665700748",
            "count": 0,
            "name": "Yueka Naezi"
        },
        {
            "id": "100088675755376",
            "count": 0,
            "name": "Jeo Montefalco Sadji"
        },
        {
            "id": "100088887104351",
            "count": 0,
            "name": "Kalix Jace Martinez"
        },
        {
            "id": "100089041035228",
            "count": 0,
            "name": "Via Maude"
        },
        {
            "id": "100089071717121",
            "count": 0,
            "name": "Kyro Geisler"
        },
        {
            "id": "100089184803890",
            "count": 0,
            "name": "Sæjî Fêî Viør Omche"
        },
        {
            "id": "100089259454697",
            "count": 0,
            "name": "Inu YA Sha"
        },
        {
            "id": "100089497879929",
            "count": 0,
            "name": "Yale Z'arxia"
        },
        {
            "id": "100089612781246",
            "count": 0,
            "name": "Mavi Sløøpy"
        },
        {
            "id": "100089624544445",
            "count": 0,
            "name": "Sam Vitale"
        },
        {
            "id": "100089662445770",
            "count": 0,
            "name": "Ahmya Hylton"
        },
        {
            "id": "100089667812152",
            "count": 0,
            "name": "Krein Veroxii Phoxirone"
        },
        {
            "id": "100089695930708",
            "count": 0,
            "name": "Jaxith"
        },
        {
            "id": "100089885145913",
            "count": 0,
            "name": "Xyan De la Cruz"
        },
        {
            "id": "100090010219479",
            "count": 0,
            "name": "James Byan"
        },
        {
            "id": "100090138493248",
            "count": 0,
            "name": "Zitty Kaith Calines"
        },
        {
            "id": "100090214917584",
            "count": 0,
            "name": "Aurellia Heaven Liegh Zyavanca"
        },
        {
            "id": "100090243831766",
            "count": 0,
            "name": "Thyra Zahira Varcaesca"
        },
        {
            "id": "100090260647959",
            "count": 0,
            "name": "Kyle Oxford"
        },
        {
            "id": "100090274616480",
            "count": 0,
            "name": "Zcyierxerriaclle Zsuzzhyxianelle Zenouskha Z'arxia"
        },
        {
            "id": "100090497120742",
            "count": 0,
            "name": "Sophia Smith"
        },
        {
            "id": "100090498295451",
            "count": 0,
            "name": "Jiya Yuj"
        },
        {
            "id": "100090555570299",
            "count": 0,
            "name": "Bella Yuj"
        },
        {
            "id": "100090650585413",
            "count": 0,
            "name": "Kaleb Tarczewski"
        },
        {
            "id": "100090654592691",
            "count": 0,
            "name": "Anastasia Quinn"
        },
        {
            "id": "100090927241810",
            "count": 0,
            "name": "Jonathan Rey"
        },
        {
            "id": "100090992310125",
            "count": 0,
            "name": "Xavier J'vrsk"
        },
        {
            "id": "100091051124538",
            "count": 0,
            "name": "Xeon Klein"
        },
        {
            "id": "100091152932437",
            "count": 0,
            "name": "Jaiden Cynth Trexoir"
        },
        {
            "id": "100091242920227",
            "count": 0,
            "name": "Yuna Montelo"
        },
        {
            "id": "100091305139263",
            "count": 0,
            "name": "Yca Fiore"
        },
        {
            "id": "100091319792809",
            "count": 0,
            "name": "Keyvara Z'arxia"
        },
        {
            "id": "100091431649260",
            "count": 0,
            "name": "Hera Haruko"
        },
        {
            "id": "100091446380331",
            "count": 0,
            "name": "Divine Santos"
        },
        {
            "id": "100091470234760",
            "count": 0,
            "name": "Celeste Smith"
        },
        {
            "id": "100091557675158",
            "count": 0,
            "name": "Ashira Ashiro"
        },
        {
            "id": "100091566003651",
            "count": 0,
            "name": "Zenoreighn Z'arxia"
        },
        {
            "id": "100091598535897",
            "count": 0,
            "name": "Zeb Tan"
        },
        {
            "id": "100091636410574",
            "count": 0,
            "name": "Yno Vercolo"
        },
        {
            "id": "100091640991984",
            "count": 0,
            "name": "Yuri Il"
        },
        {
            "id": "100091689253576",
            "count": 0,
            "name": "Savana Vior"
        },
        {
            "id": "100091749618696",
            "count": 0,
            "name": "Syx Je'ver"
        },
        {
            "id": "100091792085936",
            "count": 0,
            "name": "Joji Wu"
        },
        {
            "id": "100091811263378",
            "count": 0,
            "name": "Behatti Armstrong"
        },
        {
            "id": "100091845386011",
            "count": 0,
            "name": "Kisha Maude Z'arxia"
        },
        {
            "id": "100091925269916",
            "count": 0,
            "name": "Facebook user"
        },
        {
            "id": "100091942812158",
            "count": 0,
            "name": "Aeysha Fujinx"
        },
        {
            "id": "100091957926852",
            "count": 0,
            "name": "Brittany Gvani Z'arxia"
        },
        {
            "id": "100091959339187",
            "count": 0,
            "name": "Khai Ksks"
        },
        {
            "id": "100091972303801",
            "count": 0,
            "name": "David Zachary"
        },
        {
            "id": "100091982292949",
            "count": 0,
            "name": "Lliam Vior"
        },
        {
            "id": "100092041630302",
            "count": 0,
            "name": "Chen Chan Sue Rehld"
        },
        {
            "id": "100092096341168",
            "count": 0,
            "name": "Facebook user"
        },
        {
            "id": "100092226960610",
            "count": 0,
            "name": "Stevé Donør"
        },
        {
            "id": "100092290023448",
            "count": 0,
            "name": "Solene Maude"
        },
        {
            "id": "100092291899287",
            "count": 0,
            "name": "Delancy Soreen Z'arxia"
        },
        {
            "id": "100092347736695",
            "count": 0,
            "name": "Kalix Jace Martinez"
        },
        {
            "id": "100092389236756",
            "count": 0,
            "name": "Luna Ryu"
        },
        {
            "id": "100092423284488",
            "count": 0,
            "name": "Ethan Ryu"
        },
        {
            "id": "100092448420484",
            "count": 0,
            "name": "Luna Ysha"
        },
        {
            "id": "100092555448025",
            "count": 0,
            "name": "Yin Dmp"
        },
        {
            "id": "100092557936946",
            "count": 0,
            "name": "Valentiana Borja"
        },
        {
            "id": "100092623511356",
            "count": 0,
            "name": "Jhaniel Z'arxio"
        },
        {
            "id": "100092683999049",
            "count": 0,
            "name": "Akisha Leigh Ynarez"
        },
        {
            "id": "100092729915933",
            "count": 0,
            "name": "Diego Cerujano"
        },
        {
            "id": "100092730618083",
            "count": 0,
            "name": "Yxie Maude"
        },
        {
            "id": "100092744559305",
            "count": 0,
            "name": "Kiro Cerujano"
        },
        {
            "id": "100092753822065",
            "count": 0,
            "name": "Kurt Oxford"
        },
        {
            "id": "100092869911648",
            "count": 0,
            "name": "Norylie"
        },
        {
            "id": "100092936231836",
            "count": 0,
            "name": "Lysandra Thalia Maeve"
        },
        {
            "id": "100092982437773",
            "count": 0,
            "name": "Selene Ray"
        },
        {
            "id": "100093041253586",
            "count": 0,
            "name": "Natha Lia"
        },
        {
            "id": "100093209922752",
            "count": 0,
            "name": "Lunna Celeste Montefalco"
        },
        {
            "id": "100093249843329",
            "count": 0,
            "name": "Ace Supremo"
        },
        {
            "id": "100093281914725",
            "count": 0,
            "name": "Nash V Yen"
        },
        {
            "id": "100093305431364",
            "count": 0,
            "name": "Caesar Z'arxio"
        },
        {
            "id": "100093316270634",
            "count": 0,
            "name": "Avia Louis"
        },
        {
            "id": "100093337959838",
            "count": 0,
            "name": "Kalix Ferer"
        },
        {
            "id": "100093343144940",
            "count": 0,
            "name": "Flavie Via Ernesta"
        },
        {
            "id": "100079655854751",
            "count": 0,
            "name": "Axerylle Zy D'olorous"
        },
        {
            "id": "100091342400216",
            "count": 0,
            "name": "Quizy Aeiverquesseah"
        },
        {
            "id": "100056962911456",
            "count": 0,
            "name": "Feneithrelyn Hiyori"
        }
    ],
    "day": [
        {
            "id": "100015784159494",
            "count": 0,
            "name": "Jhon Xyryll Samoy"
        },
        {
            "id": "100029946503614",
            "count": 0,
            "name": "Arnel Cabael Elecionez"
        },
        {
            "id": "100052256795455",
            "count": 0,
            "name": "Aizlo Gezu"
        },
        {
            "id": "100053613574876",
            "count": 0,
            "name": "Thraia Ycà Kriffney"
        },
        {
            "id": "100056442510902",
            "count": 0,
            "name": "Xeon Klien"
        },
        {
            "id": "100057336722373",
            "count": 0,
            "name": "Mayumi Oxford"
        },
        {
            "id": "100063457657253",
            "count": 0,
            "name": "Yassy Tuwsi Montreux"
        },
        {
            "id": "100063756061243",
            "count": 0,
            "name": "Kiel Dursero"
        },
        {
            "id": "100067497300792",
            "count": 0,
            "name": "Justin Z'arxio"
        },
        {
            "id": "100068296688286",
            "count": 0,
            "name": "Ken Ewo Smith Z'arxio"
        },
        {
            "id": "100068424046111",
            "count": 0,
            "name": "Axel Kai Seviller"
        },
        {
            "id": "100068750480443",
            "count": 0,
            "name": "Cressida Astrid"
        },
        {
            "id": "100068842388506",
            "count": 0,
            "name": "Krianquin Rae"
        },
        {
            "id": "100068888551337",
            "count": 0,
            "name": "Kd Ador"
        },
        {
            "id": "100069341480870",
            "count": 0,
            "name": "Maya Aria P'rrty"
        },
        {
            "id": "100069347376706",
            "count": 0,
            "name": "Yuno"
        },
        {
            "id": "100069436000106",
            "count": 0,
            "name": "Keilyn Echavez"
        },
        {
            "id": "100071147416496",
            "count": 0,
            "name": "Clint Medidas"
        },
        {
            "id": "100072316457174",
            "count": 0,
            "name": "Jeyv Cussea"
        },
        {
            "id": "100072333138502",
            "count": 0,
            "name": "Yvà Snowlly"
        },
        {
            "id": "100072464087782",
            "count": 0,
            "name": "Zyrine Claire Dela Cruz"
        },
        {
            "id": "100072861848340",
            "count": 0,
            "name": "Akhira Montefalcon"
        },
        {
            "id": "100072868715963",
            "count": 0,
            "name": "Saji Yvette Sj'rve"
        },
        {
            "id": "100072990777373",
            "count": 0,
            "name": "Unice Sløøpy"
        },
        {
            "id": "100073359132347",
            "count": 0,
            "name": "Enzo J'vgsk"
        },
        {
            "id": "100073923792201",
            "count": 0,
            "name": "Yxie Scjevor"
        },
        {
            "id": "100074102111403",
            "count": 0,
            "name": "Shiro Mistuoten"
        },
        {
            "id": "100074788670733",
            "count": 0,
            "name": "Devi Wu"
        },
        {
            "id": "100075056864256",
            "count": 0,
            "name": "Sebastian Cameron"
        },
        {
            "id": "100075194042673",
            "count": 0,
            "name": "Nixy Nixcy Hoe"
        },
        {
            "id": "100075283802656",
            "count": 0,
            "name": "Khier Quervø"
        },
        {
            "id": "100076171426141",
            "count": 0,
            "name": "Facebook user"
        },
        {
            "id": "100076236396452",
            "count": 0,
            "name": "Kylie Xylle Brythe"
        },
        {
            "id": "100076441082770",
            "count": 0,
            "name": "Kyle D'minahal"
        },
        {
            "id": "100076661327214",
            "count": 0,
            "name": "Scarlet D'oeuvro"
        },
        {
            "id": "100076714233578",
            "count": 0,
            "name": "Luce Claire Maude"
        },
        {
            "id": "100076834916779",
            "count": 0,
            "name": "Yanna Xyreen Hyvra"
        },
        {
            "id": "100078010357356",
            "count": 0,
            "name": "Zreiy Winz"
        },
        {
            "id": "100078720609713",
            "count": 0,
            "name": "Rocky Dump"
        },
        {
            "id": "100079021125349",
            "count": 0,
            "name": "Kathlyn Nipal ʚĩɞ"
        },
        {
            "id": "100079075326714",
            "count": 0,
            "name": "Dree Swæńj"
        },
        {
            "id": "100079345951320",
            "count": 0,
            "name": "Cyca Axerylle Alcantara"
        },
        {
            "id": "100079539530322",
            "count": 0,
            "name": "ۦۦ ۦۦ ۦۦ ۦۦ"
        },
        {
            "id": "100079900270483",
            "count": 0,
            "name": "Ezèkîel Lèrwîck Cruivo"
        },
        {
            "id": "100080027797495",
            "count": 0,
            "name": "Tyron Volkzki"
        },
        {
            "id": "100080034333694",
            "count": 0,
            "name": "Bella Z'arxia"
        },
        {
            "id": "100080597322059",
            "count": 0,
            "name": "Luke Natividad"
        },
        {
            "id": "100080684537023",
            "count": 0,
            "name": "Kyle Zeus Z'arxio"
        },
        {
            "id": "100080694881574",
            "count": 0,
            "name": "Kenzo Hiroshi"
        },
        {
            "id": "100080743230165",
            "count": 0,
            "name": "Rael Rivacci"
        },
        {
            "id": "100081178122673",
            "count": 0,
            "name": "Jasmin Guifre"
        },
        {
            "id": "100081370230661",
            "count": 0,
            "name": "Akishana Viara Liyunarez Ramirez"
        },
        {
            "id": "100081499382300",
            "count": 0,
            "name": "Raze Eziekiel Salvenia"
        },
        {
            "id": "100081542657328",
            "count": 0,
            "name": "Kristelle Monvalle"
        },
        {
            "id": "100081819391260",
            "count": 0,
            "name": "Nick's Dump"
        },
        {
            "id": "100081844080766",
            "count": 0,
            "name": "Prince Kurt Delasantos"
        },
        {
            "id": "100082005732944",
            "count": 0,
            "name": "Drake Savern Lee Z'arxio"
        },
        {
            "id": "100082185965096",
            "count": 0,
            "name": "Xian Winter"
        },
        {
            "id": "100082693570014",
            "count": 0,
            "name": "Yca Z'arxia"
        },
        {
            "id": "100082996149404",
            "count": 0,
            "name": "Kai S'jvrs"
        },
        {
            "id": "100083222048188",
            "count": 0,
            "name": "Tafi S'jdior"
        },
        {
            "id": "100083314337739",
            "count": 0,
            "name": "Chloe Jane Galvez"
        },
        {
            "id": "100083320056754",
            "count": 0,
            "name": "Clark Na Magaling"
        },
        {
            "id": "100083825834857",
            "count": 0,
            "name": "Cxion Z'arxia"
        },
        {
            "id": "100083964785167",
            "count": 0,
            "name": "Audrey Z'arxia"
        },
        {
            "id": "100084182315788",
            "count": 0,
            "name": "Averiah Hyacinth"
        },
        {
            "id": "100084383060995",
            "count": 0,
            "name": "Ban Dump"
        },
        {
            "id": "100084440292351",
            "count": 0,
            "name": "Maczine Shaile Livanne"
        },
        {
            "id": "100084548494927",
            "count": 0,
            "name": "Selene Sy"
        },
        {
            "id": "100084846044769",
            "count": 0,
            "name": "Luna Montero"
        },
        {
            "id": "100085230758202",
            "count": 0,
            "name": "Beatrice Fiøre"
        },
        {
            "id": "100085236265871",
            "count": 0,
            "name": "Le Ah Z'arxia"
        },
        {
            "id": "100085255144447",
            "count": 0,
            "name": "Yvio Vior"
        },
        {
            "id": "100085290743793",
            "count": 0,
            "name": "Kíbb Qúérvø"
        },
        {
            "id": "100085327013500",
            "count": 0,
            "name": "Xaiver J'vsk"
        },
        {
            "id": "100085614473846",
            "count": 0,
            "name": "Phia Shine"
        },
        {
            "id": "100085660627867",
            "count": 0,
            "name": "Kyle Smith"
        },
        {
            "id": "100085831004499",
            "count": 0,
            "name": "Sophia Kyle"
        },
        {
            "id": "100086067229638",
            "count": 0,
            "name": "Aeisha Z'arxia ʚĩɞ"
        },
        {
            "id": "100086333457652",
            "count": 0,
            "name": "JL Dilliger"
        },
        {
            "id": "100086705957333",
            "count": 0,
            "name": "Ashley Simp"
        },
        {
            "id": "100086730093729",
            "count": 0,
            "name": "Mikaella Samantha Park - Jung"
        },
        {
            "id": "100086873086028",
            "count": 0,
            "name": "Threia Fuentabella"
        },
        {
            "id": "100087242479229",
            "count": 0,
            "name": "Aekishe Zacharielle"
        },
        {
            "id": "100087269285806",
            "count": 0,
            "name": "Kurt Smit"
        },
        {
            "id": "100087282854181",
            "count": 0,
            "name": "Zhamella Sozaine"
        },
        {
            "id": "100087417728849",
            "count": 0,
            "name": "Akiesha Jvsk"
        },
        {
            "id": "100087462635316",
            "count": 0,
            "name": "Zabby Montefalco"
        },
        {
            "id": "100087487240107",
            "count": 0,
            "name": "Rei Z'arxio"
        },
        {
            "id": "100087567420057",
            "count": 0,
            "name": "Princess Althea"
        },
        {
            "id": "100087635354804",
            "count": 0,
            "name": "Leo Dum'p"
        },
        {
            "id": "100087742362600",
            "count": 0,
            "name": "Raine"
        },
        {
            "id": "100087757128483",
            "count": 0,
            "name": "Vierfaith Suarez"
        },
        {
            "id": "100088145014968",
            "count": 0,
            "name": "Xiana Soreen"
        },
        {
            "id": "100088213791023",
            "count": 0,
            "name": "Zarchia Dump"
        },
        {
            "id": "100088402937238",
            "count": 0,
            "name": "Zaxia Reighn Churo"
        },
        {
            "id": "100088479528644",
            "count": 0,
            "name": "ZAY CAELUM LEIF"
        },
        {
            "id": "100088615035236",
            "count": 0,
            "name": "Ashiro Kulangsamwamwamwa"
        },
        {
            "id": "100088665700748",
            "count": 0,
            "name": "Yueka Naezi"
        },
        {
            "id": "100088675755376",
            "count": 0,
            "name": "Jeo Montefalco Sadji"
        },
        {
            "id": "100088887104351",
            "count": 0,
            "name": "Kalix Jace Martinez"
        },
        {
            "id": "100089041035228",
            "count": 0,
            "name": "Via Maude"
        },
        {
            "id": "100089071717121",
            "count": 0,
            "name": "Kyro Geisler"
        },
        {
            "id": "100089184803890",
            "count": 0,
            "name": "Sæjî Fêî Viør Omche"
        },
        {
            "id": "100089259454697",
            "count": 0,
            "name": "Inu YA Sha"
        },
        {
            "id": "100089497879929",
            "count": 0,
            "name": "Yale Z'arxia"
        },
        {
            "id": "100089612781246",
            "count": 0,
            "name": "Mavi Sløøpy"
        },
        {
            "id": "100089624544445",
            "count": 0,
            "name": "Sam Vitale"
        },
        {
            "id": "100089662445770",
            "count": 0,
            "name": "Ahmya Hylton"
        },
        {
            "id": "100089667812152",
            "count": 0,
            "name": "Krein Veroxii Phoxirone"
        },
        {
            "id": "100089695930708",
            "count": 0,
            "name": "Jaxith"
        },
        {
            "id": "100089885145913",
            "count": 0,
            "name": "Xyan De la Cruz"
        },
        {
            "id": "100090010219479",
            "count": 0,
            "name": "James Byan"
        },
        {
            "id": "100090138493248",
            "count": 0,
            "name": "Zitty Kaith Calines"
        },
        {
            "id": "100090214917584",
            "count": 0,
            "name": "Aurellia Heaven Liegh Zyavanca"
        },
        {
            "id": "100090243831766",
            "count": 0,
            "name": "Thyra Zahira Varcaesca"
        },
        {
            "id": "100090260647959",
            "count": 0,
            "name": "Kyle Oxford"
        },
        {
            "id": "100090274616480",
            "count": 0,
            "name": "Zcyierxerriaclle Zsuzzhyxianelle Zenouskha Z'arxia"
        },
        {
            "id": "100090497120742",
            "count": 0,
            "name": "Sophia Smith"
        },
        {
            "id": "100090498295451",
            "count": 0,
            "name": "Jiya Yuj"
        },
        {
            "id": "100090555570299",
            "count": 0,
            "name": "Bella Yuj"
        },
        {
            "id": "100090650585413",
            "count": 0,
            "name": "Kaleb Tarczewski"
        },
        {
            "id": "100090654592691",
            "count": 0,
            "name": "Anastasia Quinn"
        },
        {
            "id": "100090927241810",
            "count": 0,
            "name": "Jonathan Rey"
        },
        {
            "id": "100090992310125",
            "count": 0,
            "name": "Xavier J'vrsk"
        },
        {
            "id": "100091051124538",
            "count": 0,
            "name": "Xeon Klein"
        },
        {
            "id": "100091152932437",
            "count": 0,
            "name": "Jaiden Cynth Trexoir"
        },
        {
            "id": "100091242920227",
            "count": 0,
            "name": "Yuna Montelo"
        },
        {
            "id": "100091305139263",
            "count": 0,
            "name": "Yca Fiore"
        },
        {
            "id": "100091319792809",
            "count": 0,
            "name": "Keyvara Z'arxia"
        },
        {
            "id": "100091431649260",
            "count": 0,
            "name": "Hera Haruko"
        },
        {
            "id": "100091446380331",
            "count": 0,
            "name": "Divine Santos"
        },
        {
            "id": "100091470234760",
            "count": 0,
            "name": "Celeste Smith"
        },
        {
            "id": "100091557675158",
            "count": 0,
            "name": "Ashira Ashiro"
        },
        {
            "id": "100091566003651",
            "count": 0,
            "name": "Zenoreighn Z'arxia"
        },
        {
            "id": "100091598535897",
            "count": 0,
            "name": "Zeb Tan"
        },
        {
            "id": "100091636410574",
            "count": 0,
            "name": "Yno Vercolo"
        },
        {
            "id": "100091640991984",
            "count": 0,
            "name": "Yuri Il"
        },
        {
            "id": "100091689253576",
            "count": 0,
            "name": "Savana Vior"
        },
        {
            "id": "100091749618696",
            "count": 0,
            "name": "Syx Je'ver"
        },
        {
            "id": "100091792085936",
            "count": 0,
            "name": "Joji Wu"
        },
        {
            "id": "100091811263378",
            "count": 0,
            "name": "Behatti Armstrong"
        },
        {
            "id": "100091845386011",
            "count": 0,
            "name": "Kisha Maude Z'arxia"
        },
        {
            "id": "100091925269916",
            "count": 0,
            "name": "Facebook user"
        },
        {
            "id": "100091942812158",
            "count": 0,
            "name": "Aeysha Fujinx"
        },
        {
            "id": "100091957926852",
            "count": 0,
            "name": "Brittany Gvani Z'arxia"
        },
        {
            "id": "100091959339187",
            "count": 0,
            "name": "Khai Ksks"
        },
        {
            "id": "100091972303801",
            "count": 0,
            "name": "David Zachary"
        },
        {
            "id": "100091982292949",
            "count": 0,
            "name": "Lliam Vior"
        },
        {
            "id": "100092041630302",
            "count": 0,
            "name": "Chen Chan Sue Rehld"
        },
        {
            "id": "100092096341168",
            "count": 0,
            "name": "Facebook user"
        },
        {
            "id": "100092226960610",
            "count": 0,
            "name": "Stevé Donør"
        },
        {
            "id": "100092290023448",
            "count": 0,
            "name": "Solene Maude"
        },
        {
            "id": "100092291899287",
            "count": 0,
            "name": "Delancy Soreen Z'arxia"
        },
        {
            "id": "100092347736695",
            "count": 0,
            "name": "Kalix Jace Martinez"
        },
        {
            "id": "100092389236756",
            "count": 0,
            "name": "Luna Ryu"
        },
        {
            "id": "100092423284488",
            "count": 0,
            "name": "Ethan Ryu"
        },
        {
            "id": "100092448420484",
            "count": 0,
            "name": "Luna Ysha"
        },
        {
            "id": "100092555448025",
            "count": 0,
            "name": "Yin Dmp"
        },
        {
            "id": "100092557936946",
            "count": 0,
            "name": "Valentiana Borja"
        },
        {
            "id": "100092623511356",
            "count": 0,
            "name": "Jhaniel Z'arxio"
        },
        {
            "id": "100092683999049",
            "count": 0,
            "name": "Akisha Leigh Ynarez"
        },
        {
            "id": "100092729915933",
            "count": 0,
            "name": "Diego Cerujano"
        },
        {
            "id": "100092730618083",
            "count": 0,
            "name": "Yxie Maude"
        },
        {
            "id": "100092744559305",
            "count": 0,
            "name": "Kiro Cerujano"
        },
        {
            "id": "100092753822065",
            "count": 0,
            "name": "Kurt Oxford"
        },
        {
            "id": "100092869911648",
            "count": 0,
            "name": "Norylie"
        },
        {
            "id": "100092936231836",
            "count": 0,
            "name": "Lysandra Thalia Maeve"
        },
        {
            "id": "100092982437773",
            "count": 0,
            "name": "Selene Ray"
        },
        {
            "id": "100093041253586",
            "count": 0,
            "name": "Natha Lia"
        },
        {
            "id": "100093209922752",
            "count": 0,
            "name": "Lunna Celeste Montefalco"
        },
        {
            "id": "100093249843329",
            "count": 0,
            "name": "Ace Supremo"
        },
        {
            "id": "100093281914725",
            "count": 0,
            "name": "Nash V Yen"
        },
        {
            "id": "100093305431364",
            "count": 0,
            "name": "Caesar Z'arxio"
        },
        {
            "id": "100093316270634",
            "count": 0,
            "name": "Avia Louis"
        },
        {
            "id": "100093337959838",
            "count": 0,
            "name": "Kalix Ferer"
        },
        {
            "id": "100093343144940",
            "count": 0,
            "name": "Flavie Via Ernesta"
        },
        {
            "id": "100079655854751",
            "count": 0,
            "name": "Axerylle Zy D'olorous"
        },
        {
            "id": "100091342400216",
            "count": 0,
            "name": "Quizy Aeiverquesseah"
        },
        {
            "id": "100056962911456",
            "count": 0,
            "name": "Feneithrelyn Hiyori"
        }
    ],
    "time": 4
}