{
    "total": [
        {
            "id": "100077534254895",
            "count": 14
        },
        {
            "id": "100078420075277",
            "count": 0
        },
        {
            "id": "100079367374530",
            "count": 0
        },
        {
            "id": "100080842694701",
            "count": 0
        },
        {
            "id": "100081188702836",
            "count": 4
        },
        {
            "id": "100083728124872",
            "count": 0
        },
        {
            "id": "100084031963647",
            "count": 29
        },
        {
            "id": "100085377973382",
            "count": 0
        },
        {
            "id": "100086274230560",
            "count": 0
        },
        {
            "id": "100087633677020",
            "count": 0
        },
        {
            "id": "100087873511599",
            "count": 62
        },
        {
            "id": "100088305713118",
            "count": 0
        },
        {
            "id": "100088479528644",
            "count": 0
        },
        {
            "id": "100088832717096",
            "count": 0
        },
        {
            "id": "100088911439138",
            "count": 0
        },
        {
            "id": "100089449884212",
            "count": 0
        },
        {
            "id": "100089664621419",
            "count": 0
        },
        {
            "id": "100089749382215",
            "count": 0
        },
        {
            "id": "100090703985836",
            "count": 0
        },
        {
            "id": "100090960873954",
            "count": 17
        },
        {
            "id": "100091458636560",
            "count": 0
        },
        {
            "id": "100091469904024",
            "count": 0
        },
        {
            "id": "100091557892722",
            "count": 0
        },
        {
            "id": "100091753881072",
            "count": 9
        },
        {
            "id": "100091755979722",
            "count": 0
        },
        {
            "id": "100091839163138",
            "count": 0
        },
        {
            "id": "100091893571658",
            "count": 0
        },
        {
            "id": "100091961940461",
            "count": 0
        },
        {
            "id": "100092245410629",
            "count": 0
        },
        {
            "id": "100092247182017",
            "count": 2
        },
        {
            "id": "100089577662182",
            "count": 39
        },
        {
            "id": "100090394972596",
            "count": 2
        }
    ],
    "week": [
        {
            "id": "100077534254895",
            "count": 14
        },
        {
            "id": "100078420075277",
            "count": 0
        },
        {
            "id": "100079367374530",
            "count": 0
        },
        {
            "id": "100080842694701",
            "count": 0
        },
        {
            "id": "100081188702836",
            "count": 4
        },
        {
            "id": "100083728124872",
            "count": 0
        },
        {
            "id": "100084031963647",
            "count": 29
        },
        {
            "id": "100085377973382",
            "count": 0
        },
        {
            "id": "100086274230560",
            "count": 0
        },
        {
            "id": "100087633677020",
            "count": 0
        },
        {
            "id": "100087873511599",
            "count": 62
        },
        {
            "id": "100088305713118",
            "count": 0
        },
        {
            "id": "100088479528644",
            "count": 0
        },
        {
            "id": "100088832717096",
            "count": 0
        },
        {
            "id": "100088911439138",
            "count": 0
        },
        {
            "id": "100089449884212",
            "count": 0
        },
        {
            "id": "100089664621419",
            "count": 0
        },
        {
            "id": "100089749382215",
            "count": 0
        },
        {
            "id": "100090703985836",
            "count": 0
        },
        {
            "id": "100090960873954",
            "count": 17
        },
        {
            "id": "100091458636560",
            "count": 0
        },
        {
            "id": "100091469904024",
            "count": 0
        },
        {
            "id": "100091557892722",
            "count": 0
        },
        {
            "id": "100091753881072",
            "count": 9
        },
        {
            "id": "100091755979722",
            "count": 0
        },
        {
            "id": "100091839163138",
            "count": 0
        },
        {
            "id": "100091893571658",
            "count": 0
        },
        {
            "id": "100091961940461",
            "count": 0
        },
        {
            "id": "100092245410629",
            "count": 0
        },
        {
            "id": "100092247182017",
            "count": 2
        },
        {
            "id": "100089577662182",
            "count": 39
        },
        {
            "id": "100090394972596",
            "count": 2
        }
    ],
    "day": [
        {
            "id": "100077534254895",
            "count": 14
        },
        {
            "id": "100078420075277",
            "count": 0
        },
        {
            "id": "100079367374530",
            "count": 0
        },
        {
            "id": "100080842694701",
            "count": 0
        },
        {
            "id": "100081188702836",
            "count": 4
        },
        {
            "id": "100083728124872",
            "count": 0
        },
        {
            "id": "100084031963647",
            "count": 29
        },
        {
            "id": "100085377973382",
            "count": 0
        },
        {
            "id": "100086274230560",
            "count": 0
        },
        {
            "id": "100087633677020",
            "count": 0
        },
        {
            "id": "100087873511599",
            "count": 62
        },
        {
            "id": "100088305713118",
            "count": 0
        },
        {
            "id": "100088479528644",
            "count": 0
        },
        {
            "id": "100088832717096",
            "count": 0
        },
        {
            "id": "100088911439138",
            "count": 0
        },
        {
            "id": "100089449884212",
            "count": 0
        },
        {
            "id": "100089664621419",
            "count": 0
        },
        {
            "id": "100089749382215",
            "count": 0
        },
        {
            "id": "100090703985836",
            "count": 0
        },
        {
            "id": "100090960873954",
            "count": 17
        },
        {
            "id": "100091458636560",
            "count": 0
        },
        {
            "id": "100091469904024",
            "count": 0
        },
        {
            "id": "100091557892722",
            "count": 0
        },
        {
            "id": "100091753881072",
            "count": 9
        },
        {
            "id": "100091755979722",
            "count": 0
        },
        {
            "id": "100091839163138",
            "count": 0
        },
        {
            "id": "100091893571658",
            "count": 0
        },
        {
            "id": "100091961940461",
            "count": 0
        },
        {
            "id": "100092245410629",
            "count": 0
        },
        {
            "id": "100092247182017",
            "count": 2
        },
        {
            "id": "100089577662182",
            "count": 39
        },
        {
            "id": "100090394972596",
            "count": 2
        }
    ],
    "time": 3
}